reqpy/__init__.py
reqpy/main.py
reqpy-0.1.0.dist-info/LICENSE
reqpy-0.1.0.dist-info/WHEEL
reqpy-0.1.0.dist-info/METADATA
reqpy-0.1.0.dist-info/RECORD
