Metadata-Version: 2.1
Name: reqpy
Version: 0.1.0
Summary: Determine the minimal required Python version of a package
Home-page: https://github.com/stinodego/reqpy
License: MIT
Author: Stijn de Gooijer
Author-email: stijn@degooijer.io
Requires-Python: >=3.7,<4.0
Classifier: License :: OSI Approved :: MIT License
Classifier: Programming Language :: Python :: 3
Classifier: Programming Language :: Python :: 3.10
Classifier: Programming Language :: Python :: 3.7
Classifier: Programming Language :: Python :: 3.8
Classifier: Programming Language :: Python :: 3.9
Project-URL: Repository, https://github.com/stinodego/reqpy
